{"errors":[],"warnings":[],"namedChunkGroups":{"polyfill":{"chunks":[5,0,14],"assets":["webpack-runtime-a570b6d3f49ea960833f.js","webpack-runtime-a570b6d3f49ea960833f.js.map","commons-aa563e2611372fa98489.js","commons-aa563e2611372fa98489.js.map","polyfill-e3421763b6275266dd8d.js","polyfill-e3421763b6275266dd8d.js.map"],"children":{},"childAssets":{}},"app":{"chunks":[5,1,13,8,7,6,10,0,9],"assets":["webpack-runtime-a570b6d3f49ea960833f.js","webpack-runtime-a570b6d3f49ea960833f.js.map","styles.c177c3ff7b0b7896282b.css","styles-e9d24b1846c7d6eb9685.js","styles-e9d24b1846c7d6eb9685.js.map","framework-beda7bde9d7dca0755ce.js","framework-beda7bde9d7dca0755ce.js.map","9f96d65d-8db57c1ba6cdcdd54bd2.js","9f96d65d-8db57c1ba6cdcdd54bd2.js.map","8313d723-7769867bc44b074c293e.js","8313d723-7769867bc44b074c293e.js.map","0abf01d3-9477c97aa1f3d64f04fb.js","0abf01d3-9477c97aa1f3d64f04fb.js.map","bca8bde3-7b1aa59f165696850ee7.js","bca8bde3-7b1aa59f165696850ee7.js.map","commons-aa563e2611372fa98489.js","commons-aa563e2611372fa98489.js.map","app-40d3f01c1793867dab8b.js","app-40d3f01c1793867dab8b.js.map"],"children":{},"childAssets":{}},"component---node-modules-adobe-gatsby-theme-aio-src-pages-404-md":{"chunks":[1,3,4,2,0,11],"assets":["styles.c177c3ff7b0b7896282b.css","styles-e9d24b1846c7d6eb9685.js","styles-e9d24b1846c7d6eb9685.js.map","7deef1cd-b9cda56c1c56ff2290ab.js","7deef1cd-b9cda56c1c56ff2290ab.js.map","8b61fb39-e954b5513352e128346a.js","8b61fb39-e954b5513352e128346a.js.map","5e65052d-c6df007098e703fd7e91.js","5e65052d-c6df007098e703fd7e91.js.map","commons-aa563e2611372fa98489.js","commons-aa563e2611372fa98489.js.map","component---node-modules-adobe-gatsby-theme-aio-src-pages-404-md-30d6d39c8d11c70eedcb.js","component---node-modules-adobe-gatsby-theme-aio-src-pages-404-md-30d6d39c8d11c70eedcb.js.map"],"children":{},"childAssets":{}},"component---src-pages-index-md":{"chunks":[1,3,4,2,0,12],"assets":["styles.c177c3ff7b0b7896282b.css","styles-e9d24b1846c7d6eb9685.js","styles-e9d24b1846c7d6eb9685.js.map","7deef1cd-b9cda56c1c56ff2290ab.js","7deef1cd-b9cda56c1c56ff2290ab.js.map","8b61fb39-e954b5513352e128346a.js","8b61fb39-e954b5513352e128346a.js.map","5e65052d-c6df007098e703fd7e91.js","5e65052d-c6df007098e703fd7e91.js.map","commons-aa563e2611372fa98489.js","commons-aa563e2611372fa98489.js.map","component---src-pages-index-md-295ca1afa59b82f67d91.js","component---src-pages-index-md-295ca1afa59b82f67d91.js.map"],"children":{},"childAssets":{}}},"assetsByChunkName":{"polyfill":["webpack-runtime-a570b6d3f49ea960833f.js","commons-aa563e2611372fa98489.js","polyfill-e3421763b6275266dd8d.js"],"app":["webpack-runtime-a570b6d3f49ea960833f.js","styles.c177c3ff7b0b7896282b.css","styles-e9d24b1846c7d6eb9685.js","framework-beda7bde9d7dca0755ce.js","9f96d65d-8db57c1ba6cdcdd54bd2.js","8313d723-7769867bc44b074c293e.js","0abf01d3-9477c97aa1f3d64f04fb.js","bca8bde3-7b1aa59f165696850ee7.js","commons-aa563e2611372fa98489.js","app-40d3f01c1793867dab8b.js"],"component---node-modules-adobe-gatsby-theme-aio-src-pages-404-md":["styles.c177c3ff7b0b7896282b.css","styles-e9d24b1846c7d6eb9685.js","7deef1cd-b9cda56c1c56ff2290ab.js","8b61fb39-e954b5513352e128346a.js","5e65052d-c6df007098e703fd7e91.js","commons-aa563e2611372fa98489.js","component---node-modules-adobe-gatsby-theme-aio-src-pages-404-md-30d6d39c8d11c70eedcb.js"],"component---src-pages-index-md":["styles.c177c3ff7b0b7896282b.css","styles-e9d24b1846c7d6eb9685.js","7deef1cd-b9cda56c1c56ff2290ab.js","8b61fb39-e954b5513352e128346a.js","5e65052d-c6df007098e703fd7e91.js","commons-aa563e2611372fa98489.js","component---src-pages-index-md-295ca1afa59b82f67d91.js"]}}